{
  "kind": "collectionType",
  "collectionName": "games",
  "info": {
    "singularName": "game",
    "pluralName": "games",
    "displayName": "Game",
    "name": "game"
  },
  "options": {
    "increments": true,
    "timestamps": true,
    "draftAndPublish": true,
    "privateAttributes": ["id", "createdAt", "publishedAt", "updatedAt"]
  },
  "attributes": {
    "name": {
      "type": "string",
      "required": true
    },
    "url": {
      "type": "string",
      "required": true
    },
    "image_url": {
      "type": "string",
      "required": true
    },
    "bgg_id": {
      "type": "integer",
      "required": true
    }
  }
}
